lcu_connector_python/__init__.py
lcu_connector_python-1.0.dist-info/METADATA
lcu_connector_python-1.0.dist-info/RECORD
lcu_connector_python-1.0.dist-info/WHEEL
lcu_connector_python-1.0.dist-info/top_level.txt
python-lcu-connector/__init__.py
python_lcu_connector/__init__.py
