Metadata-Version: 2.1
Name: lcu-connector-python
Version: 1.0
Summary: Connects to the LCU
Home-page: https://github.com/Earleking/Python-LCU-Connector
Author: Earleking
Author-email: arek.fielding@gmail.com
License: MIT
Platform: UNKNOWN
